loadcredential/__init__.py
loadcredential/credentials.py
loadcredential-1.3.dist-info/LICENSE
loadcredential-1.3.dist-info/METADATA
loadcredential-1.3.dist-info/WHEEL
loadcredential-1.3.dist-info/top_level.txt
loadcredential-1.3.dist-info/RECORD
