Metadata-Version: 2.1
Name: loadcredential
Version: 1.3
Summary: A simple package to read credentials generated by systemd's LoadCredential, with a fallback on environment variables.
Author-email: Tom Hubrecht <pypi@mail.hubrecht.ovh>
License: MIT License
Project-URL: Homepage, https://github.com/Tom-Hubrecht/loadcredential
Project-URL: Repository, https://github.com/Tom-Hubrecht/loadcredential
Project-URL: Issues, https://github.com/Tom-Hubrecht/loadcredential/issues
Keywords: systemd,credentials,environment,secrets
Classifier: Development Status :: 5 - Production/Stable
Classifier: Intended Audience :: Developers
Classifier: License :: OSI Approved :: MIT License
Classifier: Programming Language :: Python :: 3
License-File: LICENSE
